{
  "type": "minecraft:generic",
  "pools": [
    {
      "rolls": 1,
      "entries": [
        {
          "type": "minecraft:item",
          "name": "minecraft:splash_potion",
          "functions": [
            {
              "function": "minecraft:set_nbt",
              "tag": "{display: {Name: '{\"text\":\"Potion of Unlimited Swiftness\",\"italic\":false}'}, custom_potion_effects: [{id: \"minecraft:speed\", amplifier: 0b, duration: -1}], CustomPotionColor: 2394879}"
            }
          ]
        }
      ],
      "functions": [
        {
          "function": "minecraft:set_count",
          "count": {
            "type": "minecraft:score",
            "target": {
              "type": "minecraft:fixed",
              "name": "$item_count"
            },
            "score": "patchwreck.variables",
            "scale": 1
          }
        }
      ]
    }
  ]
}
